cdk_blueprint/__init__.py
cdk_blueprint/infrastructure.py
cdk_blueprint/ec2/__init__.py
cdk_blueprint/ec2/vpc.py
CDK_Blueprint-0.0.2.dist-info/LICENSE
CDK_Blueprint-0.0.2.dist-info/METADATA
CDK_Blueprint-0.0.2.dist-info/NOTICE
CDK_Blueprint-0.0.2.dist-info/WHEEL
CDK_Blueprint-0.0.2.dist-info/top_level.txt
CDK_Blueprint-0.0.2.dist-info/RECORD
